Workbook

Sheet Executive_Summary
B1: SWIGGY INSTAMART — SALES & INVENTORY DASHBOARD
B2: Exploratory Data Analysis & Quick-Commerce Operational Metrics | Traditional vs. Modern Track
B5: TOTAL ORDERS | D5: GROSS GMV (INR) | F5: TOTAL DISCOUNTS | H5: NET REVENUE
B6: =COUNTA(Orders_Enriched!A2:A844) | D6: =SUM(Orders_Enriched!I2:I844) | F6: =SUM(Orders_Enriched!J2:J844) | H6: =F6-H6
B8: AVERAGE BASKET (AOV) | D8: TOTAL UNITS SOLD | F8: AVG DELIVERY TIME | H8: CRITICAL STOCK SKUS
B9: =AVERAGE(Orders_Enriched!I2:I844) | D9: =SUM(Orders_Enriched!H2:H844) | F9: =AVERAGE(Orders_Enriched!K2:K844) | H9: =COUNTIF(Products_Catalog!G2:G151, "CRITICAL")
B11: KEY TRADITIONAL vs MODERN ANALYSIS INSIGHTS
B13: 1. Missing Dark Stores Finding: | D13: Stores.csv records 25 stores, but transactions log up to Store050. Handled via IFERROR/Left-Join.
B15: 2. Real-Time Dynamic Formulas: | D15: All totals and margins are dynamically wired to Orders_Enriched and Products_Catalog sheets.
B17: 3. Inventory Safety Stocking: | D17: Products with < 100 available units are dynamically flagged with Red Conditional Formatting.
B19: 4. Quick-Commerce SLA Tracking: | D19: Orders exceeding the 20-minute delivery benchmark are flagged to assess dark store efficiency.

Sheet Products_Catalog
A1: ProductID | B1: ProductName | C1: CategoryID | D1: UnitPrice | E1: StockQuantity | F1: SupplierID | G1: StockoutRisk | H1: UnitsSold | I1: GrossProductRevenue
A2: PROD001 | B2: Amul Taaza Toned Milk 500ml | C2: CAT003 | D2: 27 | E2: 500 | F2: SUP004 | G2: =IF(E2<100, "CRITICAL", IF(E2<300, "LOW", "OPTIMAL")) | H2: =SUMIFS(Orders_Enriched!H:H, Orders_Enriched!C:C, A2) | I2: =D2*H2
A3: PROD002 | B3: Britannia Milk Bread | C3: CAT005 | D3: 45 | E3: 300 | F3: SUP005 | G3: =IF(E3<100, "CRITICAL", IF(E3<300, "LOW", "OPTIMAL")) | H3: =SUMIFS(Orders_Enriched!H:H, Orders_Enriched!C:C, A3) | I3: =D3*H3
A4: PROD003 | B4: Nestle Maggi 2-Minute Noodles | C4: CAT019 | D4: 14 | E4: 1200 | F4: SUP006 | G4: =IF(E4<100, "CRITICAL", IF(E4<300, "LOW", "OPTIMAL")) | H4: =SUMIFS(Orders_Enriched!H:H, Orders_Enriched!C:C, A4) | I4: =D4*H4
A5: PROD004 | B5: Tata Salt Iodized 1kg | C5: CAT012 | D5: 28 | E5: 800 | F5: SUP015 | G5: =IF(E5<100, "CRITICAL", IF(E5<300, "LOW", "OPTIMAL")) | H5: =SUMIFS(Orders_Enriched!H:H, Orders_Enriched!C:C, A5) | I5: =D5*H5
A6: PROD005 | B6: Ashirvaad Select Sharbati Atta 5kg | C6: CAT009 | D6: 290 | E6: 250 | F6: SUP023 | G6: =IF(E6<100, "CRITICAL", IF(E6<300, "LOW", "OPTIMAL")) | H6: =SUMIFS(Orders_Enriched!H:H, Orders_Enriched!C:C, A6) | I6: =D6*H6
A7: PROD006 | B7: Coca-Cola 750ml PET Bottle | C7: CAT007 | D7: 40 | E7: 600 | F7: SUP008 | G7: =IF(E7<100, "CRITICAL", IF(E7<300, "LOW", "OPTIMAL")) | H7: =SUMIFS(Orders_Enriched!H:H, Orders_Enriched!C:C, A7) | I7: =D7*H7
A8: PROD007 | B8: Lays India's Magic Masala 52g | C8: CAT006 | D8: 20 | E8: 1500 | F8: SUP034 | G8: =IF(E8<100, "CRITICAL", IF(E8<300, "LOW", "OPTIMAL")) | H8: =SUMIFS(Orders_Enriched!H:H, Orders_Enriched!C:C, A8) | I8: =D8*H8
A9: PROD008 | B9: Parle-G Gold Biscuits 1kg | C9: CAT025 | D9: 110 | E9: 700 | F9: SUP007 | G9: =IF(E9<100, "CRITICAL", IF(E9<300, "LOW", "OPTIMAL")) | H9: =SUMIFS(Orders_Enriched!H:H, Orders_Enriched!C:C, A9) | I9: =D9*H9
A10: PROD009 | B10: Surf Excel Easy Wash 1kg | C10: CAT016 | D10: 135 | E10: 400 | F10: SUP043 | G10: =IF(E10<100, "CRITICAL", IF(E10<300, "LOW", "OPTIMAL")) | H10: =SUMIFS(Orders_Enriched!H:H, Orders_Enriched!C:C, A10) | I10: =D10*H10
A11: PROD010 | B11: Colgate MaxFresh Toothpaste 150g | C11: CAT015 | D11: 95 | E11: 550 | F11: SUP027 | G11: =IF(E11<100, "CRITICAL", IF(E11<300, "LOW", "OPTIMAL")) | H11: =SUMIFS(Orders_Enriched!H:H, Orders_Enriched!C:C, A11) | I11: =D11*H11
A12: PROD011 | B12: Fresh Onion 1kg | C12: CAT002 | D12: 45 | E12: 800 | F12: SUP049 | G12: =IF(E12<100, "CRITICAL", IF(E12<300, "LOW", "OPTIMAL")) | H12: =SUMIFS(Orders_Enriched!H:H, Orders_Enriched!C:C, A12) | I12: =D12*H12
A13: PROD012 | B13: Fresh Tomato 1kg | C13: CAT002 | D13: 35 | E13: 900 | F13: SUP049 | G13: =IF(E13<100, "CRITICAL", IF(E13<300, "LOW", "OPTIMAL")) | H13: =SUMIFS(Orders_Enriched!H:H, Orders_Enriched!C:C, A13) | I13: =D13*H13
... A151: PROD150 | B151: Duracell Ultra AA Batteries 4-pack | C151: CAT018 | D151: 180 | E151: 500 | F151: SUP002 | G151: =IF(E151<100, "CRITICAL", IF(E151<300, "LOW", "OPTIMAL")) | H151: =SUMIFS(Orders_Enriched!H:H, Orders_Enriched!C:C, A151) | I151: =D151*H151

Sheet Orders_Enriched
A1: OrderID | B1: CustomerID | C1: ProductID | D1: StoreID | E1: DeliveryPartnerID | F1: OrderDate | G1: DeliveryDate | H1: Quantity | I1: TotalPrice | J1: DiscountApplied | K1: DeliveryTimeMinutes | L1: OrderStatus | M1: PaymentMethodID | N1: TimeOfDay | O1: ProductName | P1: UnitPrice | Q1: NetRevenue | R1: SLABreach
A2: ORD00001 | B2: CUST0041 | C2: PROD002 | D2: STORE038 | E2: DP006 | F2: 2024-08-31 00:59:00 | G2: 2024-08-31 01:16:00 | H2: 7 | I2: 767.51 | J2: 2.6 | K2: 17 | L2: Pending | M2: PAY04 | N2: Morning | O2: =INDEX(Products_Catalog!$B$2:$B$151, MATCH(C2, Products_Catalog!$A$2:$A$151, 0)) | P2: =INDEX(Products_Catalog!$D$2:$D$151, MATCH(C2, Products_Catalog!$A$2:$A$151, 0)) | Q2: =I2-J2 | R2: =IF(K2>20, "BREACH", "OK")
A3: ORD00002 | B3: CUST0050 | C3: PROD034 | D3: STORE022 | E3: DP047 | F3: 2024-08-25 06:35:00 | G3: 2024-08-25 06:53:00 | H3: 6 | I3: 123.26 | J3: 81.61 | K3: 18 | L3: Shipped | M3: PAY02 | N3: Morning | O3: =INDEX(Products_Catalog!$B$2:$B$151, MATCH(C3, Products_Catalog!$A$2:$A$151, 0)) | P3: =INDEX(Products_Catalog!$D$2:$D$151, MATCH(C3, Products_Catalog!$A$2:$A$151, 0)) | Q3: =I3-J3 | R3: =IF(K3>20, "BREACH", "OK")
A4: ORD00003 | B4: CUST0048 | C4: PROD107 | D4: STORE032 | E4: DP030 | F4: 2024-12-15 01:02:00 | G4: 2024-12-15 01:21:00 | H4: 10 | I4: 768.17 | J4: 81.81 | K4: 19 | L4: Cancelled | M4: PAY04 | N4: Morning | O4: =INDEX(Products_Catalog!$B$2:$B$151, MATCH(C4, Products_Catalog!$A$2:$A$151, 0)) | P4: =INDEX(Products_Catalog!$D$2:$D$151, MATCH(C4, Products_Catalog!$A$2:$A$151, 0)) | Q4: =I4-J4 | R4: =IF(K4>20, "BREACH", "OK")
A5: ORD00004 | B5: CUST0047 | C5: PROD013 | D5: STORE002 | E5: DP050 | F5: 2024-06-01 09:47:00 | G5: 2024-06-01 10:07:00 | H5: 1 | I5: 192.11 | J5: 97.78 | K5: 20 | L5: Delivered | M5: PAY05 | N5: Morning | O5: =INDEX(Products_Catalog!$B$2:$B$151, MATCH(C5, Products_Catalog!$A$2:$A$151, 0)) | P5: =INDEX(Products_Catalog!$D$2:$D$151, MATCH(C5, Products_Catalog!$A$2:$A$151, 0)) | Q5: =I5-J5 | R5: =IF(K5>20, "BREACH", "OK")
A6: ORD00005 | B6: CUST0047 | C6: PROD073 | D6: STORE009 | E6: DP043 | F6: 2024-03-07 01:09:00 | G6: 2024-03-07 01:30:00 | H6: 5 | I6: 248.37 | J6: 62.64 | K6: 21 | L6: Cancelled | M6: PAY02 | N6: Morning | O6: =INDEX(Products_Catalog!$B$2:$B$151, MATCH(C6, Products_Catalog!$A$2:$A$151, 0)) | P6: =INDEX(Products_Catalog!$D$2:$D$151, MATCH(C6, Products_Catalog!$A$2:$A$151, 0)) | Q6: =I6-J6 | R6: =IF(K6>20, "BREACH", "OK")
A7: ORD00006 | B7: CUST0032 | C7: PROD004 | D7: STORE037 | E7: DP043 | F7: 2024-06-09 10:51:00 | G7: 2024-06-09 11:13:00 | H7: 7 | I7: 452.66 | J7: 82.48 | K7: 22 | L7: Pending | M7: PAY01 | N7: Morning | O7: =INDEX(Products_Catalog!$B$2:$B$151, MATCH(C7, Products_Catalog!$A$2:$A$151, 0)) | P7: =INDEX(Products_Catalog!$D$2:$D$151, MATCH(C7, Products_Catalog!$A$2:$A$151, 0)) | Q7: =I7-J7 | R7: =IF(K7>20, "BREACH", "OK")
A8: ORD00007 | B8: CUST0039 | C8: PROD023 | D8: STORE006 | E8: DP028 | F8: 2024-03-18 09:54:00 | G8: 2024-03-18 10:17:00 | H8: 1 | I8: 537.41 | J8: 6.63 | K8: 23 | L8: Pending | M8: PAY01 | N8: Morning | O8: =INDEX(Products_Catalog!$B$2:$B$151, MATCH(C8, Products_Catalog!$A$2:$A$151, 0)) | P8: =INDEX(Products_Catalog!$D$2:$D$151, MATCH(C8, Products_Catalog!$A$2:$A$151, 0)) | Q8: =I8-J8 | R8: =IF(K8>20, "BREACH", "OK")
A9: ORD00008 | B9: CUST0018 | C9: PROD064 | D9: STORE039 | E9: DP020 | F9: 2024-12-09 06:43:00 | G9: 2024-12-09 07:07:00 | H9: 1 | I9: 769.6 | J9: 58.42 | K9: 24 | L9: Delivered | M9: PAY05 | N9: Morning | O9: =INDEX(Products_Catalog!$B$2:$B$151, MATCH(C9, Products_Catalog!$A$2:$A$151, 0)) | P9: =INDEX(Products_Catalog!$D$2:$D$151, MATCH(C9, Products_Catalog!$A$2:$A$151, 0)) | Q9: =I9-J9 | R9: =IF(K9>20, "BREACH", "OK")
A10: ORD00009 | B10: CUST0031 | C10: PROD124 | D10: STORE049 | E10: DP039 | F10: 2024-04-17 01:38:00 | G10: 2024-04-17 02:03:00 | H10: 4 | I10: 271.32 | J10: 60.54 | K10: 25 | L10: Delivered | M10: PAY03 | N10: Morning | O10: =INDEX(Products_Catalog!$B$2:$B$151, MATCH(C10, Products_Catalog!$A$2:$A$151, 0)) | P10: =INDEX(Products_Catalog!$D$2:$D$151, MATCH(C10, Products_Catalog!$A$2:$A$151, 0)) | Q10: =I10-J10 | R10: =IF(K10>20, "BREACH", "OK")
A11: ORD00010 | B11: CUST0048 | C11: PROD084 | D11: STORE012 | E11: DP046 | F11: 2024-09-22 06:04:00 | G11: 2024-09-22 06:30:00 | H11: 5 | I11: 790.08 | J11: 67.07 | K11: 26 | L11: Pending | M11: PAY04 | N11: Morning | O11: =INDEX(Products_Catalog!$B$2:$B$151, MATCH(C11, Products_Catalog!$A$2:$A$151, 0)) | P11: =INDEX(Products_Catalog!$D$2:$D$151, MATCH(C11, Products_Catalog!$A$2:$A$151, 0)) | Q11: =I11-J11 | R11: =IF(K11>20, "BREACH", "OK")
A12: ORD00011 | B12: CUST0033 | C12: PROD066 | D12: STORE043 | E12: DP031 | F12: 2024-02-17 04:12:00 | G12: 2024-02-17 04:39:00 | H12: 7 | I12: 693.96 | J12: 64.98 | K12: 27 | L12: Cancelled | M12: PAY01 | N12: Morning | O12: =INDEX(Products_Catalog!$B$2:$B$151, MATCH(C12, Products_Catalog!$A$2:$A$151, 0)) | P12: =INDEX(Products_Catalog!$D$2:$D$151, MATCH(C12, Products_Catalog!$A$2:$A$151, 0)) | Q12: =I12-J12 | R12: =IF(K12>20, "BREACH", "OK")
A13: ORD00012 | B13: CUST0036 | C13: PROD102 | D13: STORE033 | E13: DP017 | F13: 2024-04-21 10:40:00 | G13: 2024-04-21 11:08:00 | H13: 5 | I13: 110.41 | J13: 3.71 | K13: 28 | L13: Delivered | M13: PAY03 | N13: Morning | O13: =INDEX(Products_Catalog!$B$2:$B$151, MATCH(C13, Products_Catalog!$A$2:$A$151, 0)) | P13: =INDEX(Products_Catalog!$D$2:$D$151, MATCH(C13, Products_Catalog!$A$2:$A$151, 0)) | Q13: =I13-J13 | R13: =IF(K13>20, "BREACH", "OK")
... A842: ORD02000 | B842: CUST0040 | C842: PROD047 | D842: STORE049 | E842: DP030 | F842: 2024-08-07 14:25:00 | G842: 2024-08-07 14:47:00 | H842: 7 | I842: 2426.9 | J842: 308.52 | K842: 22 | L842: Pending | M842: PAY02 | N842: Afternoon | O842: =INDEX(Products_Catalog!$B$2:$B$151, MATCH(C842, Products_Catalog!$A$2:$A$151, 0)) | P842: =INDEX(Products_Catalog!$D$2:$D$151, MATCH(C842, Products_Catalog!$A$2:$A$151, 0)) | Q842: =I842-J842 | R842: =IF(K842>20, "BREACH", "OK")

Sheet Category_Performance
A1: CategoryID | B1: CategoryName | C1: Subcategory | D1: ProductCount | E1: TotalUnitsSold | F1: GrossRevenue | G1: ShareOfRevenue
A2: CAT001 | B2: Fruits & Vegetables | C2: Fresh Fruits | D2: =COUNTIF(Products_Catalog!C:C, A2) | E2: =SUMIF(Products_Catalog!C:C, A2, Products_Catalog!H:H) | F2: =SUMIF(Products_Catalog!C:C, A2, Products_Catalog!I:I) | G2: =F2/Executive_Summary!$H$6
A3: CAT002 | B3: Fruits & Vegetables | C3: Fresh Vegetables | D3: =COUNTIF(Products_Catalog!C:C, A3) | E3: =SUMIF(Products_Catalog!C:C, A3, Products_Catalog!H:H) | F3: =SUMIF(Products_Catalog!C:C, A3, Products_Catalog!I:I) | G3: =F3/Executive_Summary!$H$6
A4: CAT003 | B4: Dairy & Bread | C4: Milk & Curd | D4: =COUNTIF(Products_Catalog!C:C, A4) | E4: =SUMIF(Products_Catalog!C:C, A4, Products_Catalog!H:H) | F4: =SUMIF(Products_Catalog!C:C, A4, Products_Catalog!I:I) | G4: =F4/Executive_Summary!$H$6
A5: CAT004 | B5: Dairy & Bread | C5: Cheese & Butter | D5: =COUNTIF(Products_Catalog!C:C, A5) | E5: =SUMIF(Products_Catalog!C:C, A5, Products_Catalog!H:H) | F5: =SUMIF(Products_Catalog!C:C, A5, Products_Catalog!I:I) | G5: =F5/Executive_Summary!$H$6
A6: CAT005 | B6: Dairy & Bread | C6: Bread & Buns | D6: =COUNTIF(Products_Catalog!C:C, A6) | E6: =SUMIF(Products_Catalog!C:C, A6, Products_Catalog!H:H) | F6: =SUMIF(Products_Catalog!C:C, A6, Products_Catalog!I:I) | G6: =F6/Executive_Summary!$H$6
A7: CAT006 | B7: Snacks & Beverages | C7: Chips & Crisps | D7: =COUNTIF(Products_Catalog!C:C, A7) | E7: =SUMIF(Products_Catalog!C:C, A7, Products_Catalog!H:H) | F7: =SUMIF(Products_Catalog!C:C, A7, Products_Catalog!I:I) | G7: =F7/Executive_Summary!$H$6
A8: CAT007 | B8: Snacks & Beverages | C8: Cold Drinks | D8: =COUNTIF(Products_Catalog!C:C, A8) | E8: =SUMIF(Products_Catalog!C:C, A8, Products_Catalog!H:H) | F8: =SUMIF(Products_Catalog!C:C, A8, Products_Catalog!I:I) | G8: =F8/Executive_Summary!$H$6
A9: CAT008 | B9: Snacks & Beverages | C9: Tea & Coffee | D9: =COUNTIF(Products_Catalog!C:C, A9) | E9: =SUMIF(Products_Catalog!C:C, A9, Products_Catalog!H:H) | F9: =SUMIF(Products_Catalog!C:C, A9, Products_Catalog!I:I) | G9: =F9/Executive_Summary!$H$6
A10: CAT009 | B10: Staples | C10: Atta & Flours | D10: =COUNTIF(Products_Catalog!C:C, A10) | E10: =SUMIF(Products_Catalog!C:C, A10, Products_Catalog!H:H) | F10: =SUMIF(Products_Catalog!C:C, A10, Products_Catalog!I:I) | G10: =F10/Executive_Summary!$H$6
A11: CAT010 | B11: Staples | C11: Rice & Grains | D11: =COUNTIF(Products_Catalog!C:C, A11) | E11: =SUMIF(Products_Catalog!C:C, A11, Products_Catalog!H:H) | F11: =SUMIF(Products_Catalog!C:C, A11, Products_Catalog!I:I) | G11: =F11/Executive_Summary!$H$6
A12: CAT011 | B12: Staples | C12: Dals & Pulses | D12: =COUNTIF(Products_Catalog!C:C, A12) | E12: =SUMIF(Products_Catalog!C:C, A12, Products_Catalog!H:H) | F12: =SUMIF(Products_Catalog!C:C, A12, Products_Catalog!I:I) | G12: =F12/Executive_Summary!$H$6
A13: CAT012 | B13: Staples | C13: Oils & Ghee | D13: =COUNTIF(Products_Catalog!C:C, A13) | E13: =SUMIF(Products_Catalog!C:C, A13, Products_Catalog!H:H) | F13: =SUMIF(Products_Catalog!C:C, A13, Products_Catalog!I:I) | G13: =F13/Executive_Summary!$H$6
... A26: CAT025 | B26: Bakery & Biscuits | C26: Cookies & Biscuits | D26: =COUNTIF(Products_Catalog!C:C, A26) | E26: =SUMIF(Products_Catalog!C:C, A26, Products_Catalog!H:H) | F26: =SUMIF(Products_Catalog!C:C, A26, Products_Catalog!I:I) | G26: =F26/Executive_Summary!$H$6
B27: TOTAL | D27: =SUM(D2:D26) | E27: =SUM(E2:E26) | F27: =SUM(F2:F26) | G27: =SUM(G2:G26)

Sheet Time_and_Status_Analysis
A1: ORDER STATUS ANALYSIS
A2: OrderStatus | B2: OrderCount | C2: Percentage | D2: TotalRevenue
A3: Delivered | B3: =COUNTIF(Orders_Enriched!L:L, "Delivered") | C3: =B3/COUNTA(Orders_Enriched!A2:A844) | D3: =SUMIF(Orders_Enriched!L:L, "Delivered", Orders_Enriched!I:I)
A4: Shipped | B4: =COUNTIF(Orders_Enriched!L:L, "Shipped") | C4: =B4/COUNTA(Orders_Enriched!A2:A844) | D4: =SUMIF(Orders_Enriched!L:L, "Shipped", Orders_Enriched!I:I)
A5: Pending | B5: =COUNTIF(Orders_Enriched!L:L, "Pending") | C5: =B5/COUNTA(Orders_Enriched!A2:A844) | D5: =SUMIF(Orders_Enriched!L:L, "Pending", Orders_Enriched!I:I)
A6: Cancelled | B6: =COUNTIF(Orders_Enriched!L:L, "Cancelled") | C6: =B6/COUNTA(Orders_Enriched!A2:A844) | D6: =SUMIF(Orders_Enriched!L:L, "Cancelled", Orders_Enriched!I:I)
A9: TIME OF DAY VELOCITY
A10: TimeOfDay | B10: OrderCount | C10: Share | D10: AvgDeliveryMinutes
A11: Morning | B11: =COUNTIF(Orders_Enriched!N:N, "Morning") | C11: =B11/COUNTA(Orders_Enriched!A2:A844) | D11: =AVERAGEIF(Orders_Enriched!N:N, "Morning", Orders_Enriched!K:K)
A12: Afternoon | B12: =COUNTIF(Orders_Enriched!N:N, "Afternoon") | C12: =B12/COUNTA(Orders_Enriched!A2:A844) | D12: =AVERAGEIF(Orders_Enriched!N:N, "Afternoon", Orders_Enriched!K:K)
A13: Evening | B13: =COUNTIF(Orders_Enriched!N:N, "Evening") | C13: =B13/COUNTA(Orders_Enriched!A2:A844) | D13: =AVERAGEIF(Orders_Enriched!N:N, "Evening", Orders_Enriched!K:K)
A14: Night | B14: =COUNTIF(Orders_Enriched!N:N, "Night") | C14: =B14/COUNTA(Orders_Enriched!A2:A844) | D14: =AVERAGEIF(Orders_Enriched!N:N, "Night", Orders_Enriched!K:K)

Sheet Stores_Reference
A1: StoreID | B1: AddressID | C1: WarehouseCapacity
A2: STORE001 | B2: ADDR023 | C2: 15000
A3: STORE002 | B3: ADDR041 | C3: 18000
A4: STORE003 | B4: ADDR061 | C4: 20000
A5: STORE004 | B5: ADDR024 | C5: 12000
A6: STORE005 | B6: ADDR046 | C6: 16000
A7: STORE006 | B7: ADDR045 | C7: 14000
A8: STORE007 | B8: ADDR037 | C8: 17000
A9: STORE008 | B9: ADDR038 | C9: 15000
A10: STORE009 | B10: ADDR022 | C10: 13000
A11: STORE010 | B11: ADDR064 | C11: 16000
A12: STORE011 | B12: ADDR033 | C12: 14000
A13: STORE012 | B13: ADDR021 | C13: 19000
... A26: STORE025 | B26: ADDR153 | C26: 17000
